gemseo_ipopt/__init__.py
gemseo_ipopt/ipopt.py
gemseo_ipopt/settings.py
gemseo_ipopt-1.0.0.dist-info/licenses/LICENSE.txt
gemseo_ipopt-1.0.0.dist-info/METADATA
gemseo_ipopt-1.0.0.dist-info/WHEEL
gemseo_ipopt-1.0.0.dist-info/entry_points.txt
gemseo_ipopt-1.0.0.dist-info/top_level.txt
gemseo_ipopt-1.0.0.dist-info/RECORD
